CHANGELOG.rst
LICENSE
MANIFEST.in
README.rst
setup.py
dbparti/__init__.py
dbparti/admin.py
dbparti/models.py
dbparti/backends/__init__.py
dbparti/backends/exceptions.py
dbparti/backends/utilities.py
dbparti/backends/mysql/__init__.py
dbparti/backends/mysql/filters.py
dbparti/backends/mysql/partition.py
dbparti/backends/postgresql/__init__.py
dbparti/backends/postgresql/filters.py
dbparti/backends/postgresql/partition.py
dbparti/management/__init__.py
dbparti/management/commands/__init__.py
dbparti/management/commands/partition.py
django_db_parti2.egg-info/PKG-INFO
django_db_parti2.egg-info/SOURCES.txt
django_db_parti2.egg-info/dependency_links.txt
django_db_parti2.egg-info/not-zip-safe
django_db_parti2.egg-info/requires.txt
django_db_parti2.egg-info/top_level.txt