Metadata-Version: 1.1
Name: django-db-parti2
Version: 0.3.5
Summary: Fully automatic database table partitioning for Django
Home-page: https://github.com/maxtepkeev/django-db-parti
Author: Max Tepkeev
Author-email: tepkeev@gmail.com
License: Copyright (c) 2014 Max Tepkeev
